minerva_dispatcher/__init__.py
minerva_dispatcher/error.py
minerva_dispatcher/harvestjobsource.py
minerva_dispatcher/jobsource.py
minerva_dispatcher/pika_publisher.py
minerva_dispatcher/version.py
minerva_dispatcher/defaults/sweep-jobs.conf
minerva_dispatcher-5.0.post0.dev3.dist-info/DESCRIPTION.rst
minerva_dispatcher-5.0.post0.dev3.dist-info/METADATA
minerva_dispatcher-5.0.post0.dev3.dist-info/RECORD
minerva_dispatcher-5.0.post0.dev3.dist-info/WHEEL
minerva_dispatcher-5.0.post0.dev3.dist-info/metadata.json
minerva_dispatcher-5.0.post0.dev3.dist-info/top_level.txt
minerva_dispatcher-5.0_0.dev3.data/scripts/dispatcher
