Metadata-Version: 2.0
Name: minerva-dispatcher
Version: 5.0-0.dev3
Summary: Minerva Dispatcher library and commands
Home-page: UNKNOWN
Author: Hendrikx ITC
Author-email: info@hendrikx-itc.nl
License: GPL
Platform: UNKNOWN
Requires-Python: >=3.5
Requires-Dist: configobj
Requires-Dist: minerva-etl (>=5.0.0.dev2)
Requires-Dist: pyinotify
Requires-Dist: pyyaml
Requires-Dist: pika (==0.13.0)
